talkytrend/__init__.py
talkytrend/config.py
talkytrend/main.py
talkytrend/handler/__init__.py
talkytrend/handler/_client.py
talkytrend/handler/alphavantage.py
talkytrend/handler/calendar.py
talkytrend/handler/feed.py
talkytrend/handler/finage.py
talkytrend/handler/finnhub.py
talkytrend/handler/forexnewsapi.py
talkytrend/handler/livetv.py
talkytrend/handler/marketaux.py
talkytrend/handler/newsfilterio.py
talkytrend/handler/polygon.py
talkytrend/handler/scraper.py
talkytrend/handler/tradermade.py
talkytrend/handler/tradingeconomics.py
talkytrend/handler/tradingview.py
talkytrend/handler/twelvedata.py
talkytrend/handler/websocket.py
talkytrend/handler/yfinance.py
talkytrend-4.0.1.dist-info/licenses/LICENSE
talkytrend-4.0.1.dist-info/METADATA
talkytrend-4.0.1.dist-info/WHEEL
talkytrend-4.0.1.dist-info/top_level.txt
talkytrend-4.0.1.dist-info/RECORD
