Metadata-Version: 2.4
Name: talkytrend
Version: 4.0.1
Summary: A python package to retrieve  economic data such as Trend for any financial symbol.
Author-email: mraniki <8766259+mraniki@users.noreply.github.com>
License-Expression: MIT
Project-URL: Homepage, https://github.com/mraniki/talkytrend
Project-URL: Changelog, https://github.com/mraniki/talkytrend/blob/dev/CHANGELOG.rst
Project-URL: Support, https://github.com/mraniki/talkytrend/discussions
Project-URL: Issues, https://github.com/mraniki/talkytrend/issues
Keywords: finance,crypto,bot,trend,economic
Classifier: Programming Language :: Python :: 3
Classifier: Programming Language :: Python :: 3.10
Classifier: Programming Language :: Python :: 3.11
Classifier: Programming Language :: Python :: 3.12
Requires-Python: >=3.10
License-File: LICENSE
Requires-Dist: dynaconf>=3.1.12
Requires-Dist: loguru>=0.6.0
Requires-Dist: aiohttp>=3.8.4
Requires-Dist: xmltodict
Requires-Dist: prettytable>=3.8.0
Requires-Dist: tradingview_ta>=3.3.0
Requires-Dist: yfinance>=0.2.25
Requires-Dist: finnhub-python==2.4.23
Requires-Dist: alpha_vantage==3.0.0
Requires-Dist: twelvedata==1.2.24
Requires-Dist: tradingeconomics>=4.3.12
Provides-Extra: dev
Requires-Dist: python-semantic-release>=8.0.8; extra == "dev"
Requires-Dist: ruff~=0.9; extra == "dev"
Requires-Dist: pre-commit~=4.0; extra == "dev"
Provides-Extra: test
Requires-Dist: pytest~=7.0; extra == "test"
Requires-Dist: pytest-cov~=6.0; extra == "test"
Requires-Dist: pytest-asyncio~=0.23; extra == "test"
Requires-Dist: pytest-mock~=3.11; extra == "test"
Requires-Dist: pytest-loguru~=0.3; extra == "test"
Provides-Extra: docs
Requires-Dist: sphinx==7.4.7; extra == "docs"
Requires-Dist: pydata-sphinx-theme~=0.16; extra == "docs"
Requires-Dist: sphinx-hoverxref~=1.3; extra == "docs"
Requires-Dist: sphinx_design~=0.6; extra == "docs"
Requires-Dist: sphinx_copybutton~=0.5; extra == "docs"
Requires-Dist: myst_parser~=4.0; extra == "docs"
Dynamic: license-file
